setup.py
bin/dockerstack
dockerstack_agent/__init__.py
dockerstack_agent/builder.py
dockerstack_agent/instructions.py
dockerstack_agent.egg-info/PKG-INFO
dockerstack_agent.egg-info/SOURCES.txt
dockerstack_agent.egg-info/dependency_links.txt
dockerstack_agent.egg-info/top_level.txt