Metadata-Version: 1.1
Name: dockerstack-agent
Version: 0.1.0
Summary: Build dockerfiles without docker
Home-page: https://bitbucket.org/clouda/dockerstack
Author: Adam Thurlow
Author-email: thurloat@gmail.com
License: UNKNOWN
Platform: UNKNOWN
Classifier: Intended Audience :: Developers
Classifier: Natural Language :: English
Classifier: Programming Language :: Python
Classifier: Programming Language :: Python :: 2.7
